pytorch_beam_search/__init__.py
pytorch_beam_search/autoregressive/__init__.py
pytorch_beam_search/autoregressive/index.py
pytorch_beam_search/autoregressive/models.py
pytorch_beam_search/autoregressive/search_algorithms.py
pytorch_beam_search/seq2seq/__init__.py
pytorch_beam_search/seq2seq/index.py
pytorch_beam_search/seq2seq/models.py
pytorch_beam_search/seq2seq/search_algorithms.py
pytorch_beam_search-1.2.2.dist-info/LICENSE
pytorch_beam_search-1.2.2.dist-info/METADATA
pytorch_beam_search-1.2.2.dist-info/WHEEL
pytorch_beam_search-1.2.2.dist-info/top_level.txt
pytorch_beam_search-1.2.2.dist-info/RECORD
