Metadata-Version: 2.1
Name: pytorch-beam-search
Version: 1.2.2
Summary: A simple library that implements search algorithms for sequence models written in PyTorch.
Home-page: https://github.com/jarobyte91/pytorch_beam_search
Author: Juan Ramirez-Orta
Author-email: jarobyte91@gmail.com
Project-URL: Bug Tracker, https://github.com/jarobyte91/pytorch_beam_search/issues
Classifier: Programming Language :: Python :: 3
Classifier: License :: OSI Approved :: MIT License
Classifier: Operating System :: OS Independent
Requires-Python: >=3.6
License-File: LICENSE
Requires-Dist: certifi (>=2020.12.5)
Requires-Dist: numpy (>=1.20.3)
Requires-Dist: pandas (>=1.2.4)
Requires-Dist: python-dateutil (>=2.8.1)
Requires-Dist: pytz (>=2021.1)
Requires-Dist: six (>=1.16.0)
Requires-Dist: torch (>=1.8.1)
Requires-Dist: tqdm (>=4.61.0)
Requires-Dist: typing-extensions (>=3.10.0.0)
Requires-Dist: nltk (>=3.6.5)
